matplotsup/__init__.py
matplotsup/collatz.py
matplotsup/sort.py
matplotsup-0.0.1.dist-info/METADATA
matplotsup-0.0.1.dist-info/WHEEL
matplotsup-0.0.1.dist-info/top_level.txt
matplotsup-0.0.1.dist-info/RECORD
