Metadata-Version: 2.1
Name: matplotsup
Version: 0.0.1
Home-page: https://github.com/fireing123/pygame_phyics
Author: fireing123
Author-email: gimd82368@gmail.com
Requires-Dist: matplotlib
